[
  { "iso": "USD", "name": "US Dollar", "aliases": ["usd", "us", "dollar", "us dollar", "american"] },
  { "iso": "EUR", "name": "Euro", "aliases": ["eur", "euro"] },
  { "iso": "GBP", "name": "British Pound", "aliases": ["gbp", "pound", "sterling", "british"] },
  { "iso": "JPY", "name": "Japanese Yen", "aliases": ["jpy", "yen", "japanese"] },
  { "iso": "CHF", "name": "Swiss Franc", "aliases": ["chf", "franc", "swiss"] },
  { "iso": "CAD", "name": "Canadian Dollar", "aliases": ["cad", "canadian", "dollar", "canadian dollar"] },
  { "iso": "AUD", "name": "Australian Dollar", "aliases": ["aud", "australian", "dollar", "australian dollar"] },
  { "iso": "NZD", "name": "New Zealand Dollar", "aliases": ["nzd", "new zealand", "dollar", "kiwi"] },
  { "iso": "CNY", "name": "Chinese Yuan", "aliases": ["cny", "yuan", "renminbi", "chinese"] },
  { "iso": "HKD", "name": "Hong Kong Dollar", "aliases": ["hkd", "hong kong", "dollar"] },
  { "iso": "SGD", "name": "Singapore Dollar", "aliases": ["sgd", "singapore", "dollar"] },
  { "iso": "INR", "name": "Indian Rupee", "aliases": ["inr", "rupee", "indian"] },
  { "iso": "BRL", "name": "Brazilian Real", "aliases": ["brl", "real", "brazilian"] },
  { "iso": "ZAR", "name": "South African Rand", "aliases": ["zar", "rand", "south african"] },
  { "iso": "SEK", "name": "Swedish Krona", "aliases": ["sek", "krona", "swedish"] },
  { "iso": "NOK", "name": "Norwegian Krone", "aliases": ["nok", "krone", "norwegian"] },
  { "iso": "DKK", "name": "Danish Krone", "aliases": ["dkk", "krone", "danish"] },
  { "iso": "THB", "name": "Thai Baht", "aliases": ["thb", "baht", "thai"] },
  { "iso": "MXN", "name": "Mexican Peso", "aliases": ["mxn", "peso", "mexican"] },
  { "iso": "ARS", "name": "Argentine Peso", "aliases": ["ars", "peso", "argentine"] },
  { "iso": "PHP", "name": "Philippine Peso", "aliases": ["php", "peso", "philippine"] },
  { "iso": "KRW", "name": "South Korean Won", "aliases": ["krw", "won", "korean"] },
  { "iso": "IDR", "name": "Indonesian Rupiah", "aliases": ["idr", "rupiah", "indonesian"] },
  { "iso": "MYR", "name": "Malaysian Ringgit", "aliases": ["myr", "ringgit", "malaysian"] },
  { "iso": "PLN", "name": "Polish Zloty", "aliases": ["pln", "zloty", "polish"] },
  { "iso": "TRY", "name": "Turkish Lira", "aliases": ["try", "lira", "turkish"] },
  { "iso": "RUB", "name": "Russian Ruble", "aliases": ["rub", "ruble", "russian"] },
  { "iso": "AED", "name": "UAE Dirham", "aliases": ["aed", "dirham", "emirati"] },
  { "iso": "SAR", "name": "Saudi Riyal", "aliases": ["sar", "riyal", "saudi"] },
  { "iso": "BTC", "name": "Bitcoin", "aliases": ["btc", "bitcoin", "crypto"] }
] 